setup.py
runreveal/__init__.py
runreveal.egg-info/PKG-INFO
runreveal.egg-info/SOURCES.txt
runreveal.egg-info/dependency_links.txt
runreveal.egg-info/top_level.txt