Metadata-Version: 2.1
Name: runreveal
Version: 0.0.3
Summary: Interact with the RunReveal API
Author: Evan Johnson
Author-email: evan@runreveal.com
Classifier: Programming Language :: Python :: 3
Classifier: License :: OSI Approved :: MIT License
Classifier: Operating System :: OS Independent
Requires-Python: >=3.6
